README.md
setup.py
mc_ssh/__init__.py
mc_ssh/mccli.py
mc_ssh.egg-info/PKG-INFO
mc_ssh.egg-info/SOURCES.txt
mc_ssh.egg-info/dependency_links.txt
mc_ssh.egg-info/entry_points.txt
mc_ssh.egg-info/top_level.txt