Metadata-Version: 2.1
Name: mc-ssh
Version: 0.2.11
Summary: mc_ssh is now mccli
Home-page: UNKNOWN
License: UNKNOWN
Platform: UNKNOWN
Classifier: Development Status :: 7 - Inactive
